{
  "type": "minecraft:chest",
  "pools": [
    {
      "bonus_rolls": 0.0,
      "entries": [
        {
          "type": "minecraft:item",
          "functions": [
            {
              "add": false,
              "count": {
                "type": "minecraft:uniform",
                "max": 2.0,
                "min": 1.0
              },
              "function": "minecraft:set_count"
            }
          ],
          "name": "riskofmine:armor_piercing_rounds",
          "weight": 5
        },
        {
          "type": "minecraft:item",
          "functions": [
            {
              "add": false,
              "count": {
                "type": "minecraft:uniform",
                "max": 2.0,
                "min": 1.0
              },
              "function": "minecraft:set_count"
            }
          ],
          "name": "riskofmine:crowbar",
          "weight": 5
        },
        {
          "type": "minecraft:item",
          "functions": [
            {
              "add": false,
              "count": {
                "type": "minecraft:uniform",
                "max": 2.0,
                "min": 1.0
              },
              "function": "minecraft:set_count"
            }
          ],
          "name": "riskofmine:soldier_syringe",
          "weight": 5
        },
        {
          "type": "minecraft:item",
          "functions": [
            {
              "add": false,
              "count": {
                "type": "minecraft:uniform",
                "max": 2.0,
                "min": 1.0
              },
              "function": "minecraft:set_count"
            }
          ],
          "name": "riskofmine:bustling_fungus",
          "weight": 5
        },
        {
          "type": "minecraft:item",
          "functions": [
            {
              "add": false,
              "count": {
                "type": "minecraft:uniform",
                "max": 2.0,
                "min": 1.0
              },
              "function": "minecraft:set_count"
            }
          ],
          "name": "riskofmine:energy_drink",
          "weight": 5
        },
        {
          "type": "minecraft:item",
          "functions": [
            {
              "add": false,
              "count": {
                "type": "minecraft:uniform",
                "max": 2.0,
                "min": 1.0
              },
              "function": "minecraft:set_count"
            }
          ],
          "name": "riskofmine:focus_crystal",
          "weight": 5
        },
        {
          "type": "minecraft:item",
          "functions": [
            {
              "add": false,
              "count": {
                "type": "minecraft:uniform",
                "max": 2.0,
                "min": 1.0
              },
              "function": "minecraft:set_count"
            }
          ],
          "name": "riskofmine:gasoline",
          "weight": 5
        },
        {
          "type": "minecraft:item",
          "functions": [
            {
              "add": false,
              "count": {
                "type": "minecraft:uniform",
                "max": 2.0,
                "min": 1.0
              },
              "function": "minecraft:set_count"
            }
          ],
          "name": "riskofmine:monster_tooth",
          "weight": 5
        },
        {
          "type": "minecraft:item",
          "functions": [
            {
              "add": false,
              "count": {
                "type": "minecraft:uniform",
                "max": 2.0,
                "min": 1.0
              },
              "function": "minecraft:set_count"
            }
          ],
          "name": "riskofmine:stun_grenade",
          "weight": 5
        },
        {
          "type": "minecraft:item",
          "functions": [
            {
              "add": false,
              "count": {
                "type": "minecraft:uniform",
                "max": 1.0,
                "min": 1.0
              },
              "function": "minecraft:set_count"
            }
          ],
          "name": "riskofmine:tri_tip_dagger",
          "weight": 5
        }
      ],
      "rolls": 1.0
    }
  ],
  "random_sequence": "riskofmine:chests/small_chest"
}